{
  "name": "team-logos/QQntLLLxVawfalotWlTX.jpg",
  "bucket": "minnesota-winter-league.appspot.com",
  "metageneration": 3,
  "generation": 1757352384039,
  "contentType": "image/jpeg",
  "storageClass": "STANDARD",
  "downloadTokens": [
    "6d14abe1-1110-4a19-afcd-ac884f71a2f4"
  ],
  "etag": "z2qMjyEn22mGaNU7pC1jgWBp6tk",
  "customMetadata": {
    "teamName": "Mankato Marlins",
    "originalFileName": "54e6dd404c57a914f1dc8460962e33791c3ad6e04e50744172277ed79044cd_640.jpg",
    "uploadedAt": "2025-09-08T17:26:24.037Z"
  },
  "timeCreated": "2025-09-08T17:26:24.039Z",
  "updated": "2025-09-08T17:26:44.991Z",
  "size": 86989,
  "md5Hash": "D0a2kP5Aw868tHUhjp1ihw==",
  "crc32c": "331992201"
}