{
  "name": "team-logos/PSlbmFD05YVHnO3gQVES.jpg",
  "bucket": "minnesota-winter-league.appspot.com",
  "metageneration": 3,
  "generation": 1757352978088,
  "contentType": "image/jpeg",
  "storageClass": "STANDARD",
  "downloadTokens": [
    "819ad80b-edd5-4b56-b0d5-bf7d28ab62ae"
  ],
  "etag": "DgoMktoIX89HMOnDeDKN24MU8z4",
  "customMetadata": {
    "teamName": "Dayton Deer",
    "originalFileName": "57e7dd474f57a514f1dc8460962e33791c3ad6e04e507440722d72d29445c2_640.jpg",
    "uploadedAt": "2025-09-08T17:36:18.086Z"
  },
  "timeCreated": "2025-09-08T17:36:18.088Z",
  "updated": "2025-09-08T17:39:28.107Z",
  "size": 97599,
  "md5Hash": "K/fMl6S0pvtE95NsANmmLw==",
  "crc32c": "993122715"
}