{
  "name": "team-logos/UqmvNho6BYRqIa5zOSyY.jpg",
  "bucket": "minnesota-winter-league.appspot.com",
  "metageneration": 3,
  "generation": 1757647081497,
  "contentType": "image/jpeg",
  "storageClass": "STANDARD",
  "downloadTokens": [
    "80b2fc33-748b-4e49-a942-b75077efcaf9"
  ],
  "etag": "zQ4UAu9h5cfIufMihHnfU45OlLc",
  "customMetadata": {
    "teamName": "Cloquet Cyclones",
    "originalFileName": "g92ef828aa9808801a0eeee80cf4f63a8eeb72bac1ff5fdeaccb6c0b7512e752c388d0a5a54b5d60e366e8cc195cb77f2_640.jpg",
    "uploadedAt": "2025-09-12T03:18:01.494Z"
  },
  "timeCreated": "2025-09-12T03:18:01.497Z",
  "updated": "2025-09-12T03:19:06.816Z",
  "size": 178719,
  "md5Hash": "OJP3+Qu3qN1u2ip8Ece7xA==",
  "crc32c": "314247162"
}