{
  "name": "team-logos/9g3JNOle7mRIS5LRN84Q.jpg",
  "bucket": "minnesota-winter-league.appspot.com",
  "metageneration": 2,
  "generation": 1758060016458,
  "contentType": "image/jpeg",
  "storageClass": "STANDARD",
  "downloadTokens": [],
  "etag": "yuuKm1p5FANRbGjEpk9BU6IiIGo",
  "customMetadata": {
    "teamName": "Hastings Hornets",
    "originalFileName": "53e3d342435baa14f1dc8460962e33791c3ad6e04e507440762673d69148cd_640.jpg",
    "uploadedAt": "2025-09-16T22:00:16.456Z"
  },
  "timeCreated": "2025-09-16T22:00:16.458Z",
  "updated": "2025-09-16T22:00:16.461Z",
  "size": 34853,
  "md5Hash": "UOvMG7pNWYSGas3k7RTTag==",
  "crc32c": "842939632"
}