{
  "name": "team-logos/njDUpd72717ouVXAXjyL.jpg",
  "bucket": "minnesota-winter-league.appspot.com",
  "metageneration": 3,
  "generation": 1757352978290,
  "contentType": "image/jpeg",
  "storageClass": "STANDARD",
  "downloadTokens": [
    "4a050920-2657-4a6f-aec9-08d51d6e8f83"
  ],
  "etag": "tudvJiHddXf5iJJjef5UtJRK/9c",
  "customMetadata": {
    "teamName": "Wayzata Whales",
    "originalFileName": "55e2dd474a50b10ff3d8992cc12c30771037dbf85254794e70267cdd9444_640.jpg",
    "uploadedAt": "2025-09-08T17:36:18.288Z"
  },
  "timeCreated": "2025-09-08T17:36:18.290Z",
  "updated": "2025-09-08T17:36:36.627Z",
  "size": 115875,
  "md5Hash": "cjUy6Ldhm5BdSVg1CaobAQ==",
  "crc32c": "228487619"
}