{
  "name": "team-logos/e1fscUWkH0lttplpb215.jpg",
  "bucket": "minnesota-winter-league.appspot.com",
  "metageneration": 3,
  "generation": 1757647081273,
  "contentType": "image/jpeg",
  "storageClass": "STANDARD",
  "downloadTokens": [
    "49fa506d-ddf1-4b72-b31f-569f1f3c8207"
  ],
  "etag": "6ib5kiCqznxRoTniX3VGV0thvNs",
  "customMetadata": {
    "teamName": "Wayzata Walruses",
    "originalFileName": "hammock-2036336_640.jpg",
    "uploadedAt": "2025-09-12T03:18:01.271Z"
  },
  "timeCreated": "2025-09-12T03:18:01.273Z",
  "updated": "2025-09-12T03:19:10.296Z",
  "size": 84808,
  "md5Hash": "rUFZ4AuVi0x32NDSNzfM3g==",
  "crc32c": "616384928"
}