{
  "name": "team-logos/atL37dkvGiNp2fjPbja5.jpg",
  "bucket": "minnesota-winter-league.appspot.com",
  "metageneration": 3,
  "generation": 1757351255067,
  "contentType": "image/jpeg",
  "storageClass": "STANDARD",
  "downloadTokens": [
    "c0798092-78c2-499b-874a-34c544a6ba0f"
  ],
  "etag": "zgHB5e+A+/tTpvOTGjwABm092TE",
  "customMetadata": {
    "teamName": "Fergus Falls Fighters",
    "originalFileName": "g5900afbace889449de13b9517d62c4523c263e41fb608327c8cc26f1ad4e5b85f9414b61f23590fe1db589b27a043bf2_640.jpg",
    "uploadedAt": "2025-09-08T17:07:35.065Z"
  },
  "timeCreated": "2025-09-08T17:07:35.067Z",
  "updated": "2025-09-08T17:07:54.102Z",
  "size": 93933,
  "md5Hash": "6UvOTPulIi1egpiemA9/Nw==",
  "crc32c": "3114747275"
}