{
  "name": "team-logos/gqt7Mzx3Mkpf3QAh25k7.jpg",
  "bucket": "minnesota-winter-league.appspot.com",
  "metageneration": 2,
  "generation": 1757352526652,
  "contentType": "image/jpeg",
  "storageClass": "STANDARD",
  "downloadTokens": [],
  "etag": "BaEzW3b58MsyInsYoy3eh0PP864",
  "customMetadata": {
    "teamName": "Chanhassen Cranes",
    "originalFileName": "53e3d44a4e5baa14f1dc8460962e33791c3ad6e04e507440762e7ad3964acc_640.jpg",
    "uploadedAt": "2025-09-08T17:28:46.650Z"
  },
  "timeCreated": "2025-09-08T17:28:46.652Z",
  "updated": "2025-09-08T17:28:46.653Z",
  "size": 104199,
  "md5Hash": "YFKLUIdH0jBaXoBmxGRRQw==",
  "crc32c": "1107173712"
}