{
  "name": "team-logos/VlIqMDrTGQH7DvzvVxzV.jpg",
  "bucket": "minnesota-winter-league.appspot.com",
  "metageneration": 3,
  "generation": 1757647081482,
  "contentType": "image/jpeg",
  "storageClass": "STANDARD",
  "downloadTokens": [
    "6d3e739b-0ff2-432b-b0a5-8c2a97b9a430"
  ],
  "etag": "jp5S+REdGsilSZwlPo99smlZ9CQ",
  "customMetadata": {
    "teamName": "Grand Rapids Guardians",
    "originalFileName": "52e9d3414854aa14f1dc8460962e33791c3ad6e04e507441722a72dd964bc7_640.jpg",
    "uploadedAt": "2025-09-12T03:18:01.480Z"
  },
  "timeCreated": "2025-09-12T03:18:01.482Z",
  "updated": "2025-09-12T03:19:06.895Z",
  "size": 53259,
  "md5Hash": "5ECJsikLExzay8gD3SZhhA==",
  "crc32c": "3400639265"
}