{
  "name": "team-logos/jLcY73KMUaSeAWS2LdnN.jpg",
  "bucket": "minnesota-winter-league.appspot.com",
  "metageneration": 2,
  "generation": 1757350554716,
  "contentType": "image/jpeg",
  "storageClass": "STANDARD",
  "downloadTokens": [],
  "etag": "3VU+yRWK5F8JkpEGLzlI51QsS7o",
  "customMetadata": {
    "teamName": "Maple Grove Mantises",
    "originalFileName": "5ee6d6454d57b10ff3d8992cc12c30771037dbf852547848702a7ed4974c_640.jpg",
    "uploadedAt": "2025-09-08T16:55:54.714Z"
  },
  "timeCreated": "2025-09-08T16:55:54.716Z",
  "updated": "2025-09-08T16:55:54.717Z",
  "size": 47148,
  "md5Hash": "AOh4EcZI3Kl34xSH/VvfSw==",
  "crc32c": "2016092881"
}